sigur/__init__.py
sigur/sigur.py
sigur_connector-0.0.5.dist-info/DESCRIPTION.rst
sigur_connector-0.0.5.dist-info/METADATA
sigur_connector-0.0.5.dist-info/RECORD
sigur_connector-0.0.5.dist-info/WHEEL
sigur_connector-0.0.5.dist-info/metadata.json
sigur_connector-0.0.5.dist-info/top_level.txt
